ssh_ansible/__init__.py
ssh_ansible/ansible_ssh.py
ssh_ansible-1.0.0.dist-info/licenses/LICENSE
ssh_ansible-1.0.0.dist-info/METADATA
ssh_ansible-1.0.0.dist-info/WHEEL
ssh_ansible-1.0.0.dist-info/entry_points.txt
ssh_ansible-1.0.0.dist-info/top_level.txt
ssh_ansible-1.0.0.dist-info/RECORD
