Metadata-Version: 2.4
Name: ssh_ansible
Version: 1.0.0
Summary: SSH to host from ansible inventory
Home-page: https://github.com/marekruzicka/ansible-ssh.git
Author: Marek Ruzicka
Author-email: pypi@glide.sk
License: MIT
Classifier: Development Status :: 5 - Production/Stable
Classifier: Programming Language :: Python :: 3
Classifier: Operating System :: POSIX :: Linux
Classifier: Environment :: Console
License-File: LICENSE
Requires-Dist: ansible-core>=2.9
Provides-Extra: dev
Requires-Dist: twine>=6.1; extra == "dev"
Dynamic: author
Dynamic: author-email
Dynamic: classifier
Dynamic: description
Dynamic: description-content-type
Dynamic: home-page
Dynamic: license
Dynamic: license-file
Dynamic: provides-extra
Dynamic: requires-dist
Dynamic: summary
